negima/__init__.py
negima/merger.py
negima/parser.py
negima/rule.py
negima-0.1.3.dist-info/METADATA
negima-0.1.3.dist-info/RECORD
negima-0.1.3.dist-info/WHEEL
negima-0.1.3.dist-info/top_level.txt
