Metadata-Version: 2.1
Name: negima
Version: 0.1.3
Summary: Extract phrases in Japanese text by using the part-of-speeches based rules you defined.
Home-page: https://github.com/cocodrips/negima
Author: cocodrips
Author-email: cocodrips@gmail.com
License: MIT
Platform: UNKNOWN
Classifier: Programming Language :: Python :: 3
Requires-Python: >=3.4
Provides-Extra: dev
Requires-Dist: mecab-python3 (>=0.7)
Requires-Dist: pandas (>=0.19)
Requires-Dist: xlrd (>=1.1.0)
Provides-Extra: dev
Requires-Dist: pytest (>=3); extra == 'dev'
